{"LeagueName":"ACC Men's Premier Cup","CategoryName":"ACC Premier Cup","StatusOrTime":"Finished","StatusComment":"Nepal win by 68 runs","Phase":"Non Official One Day (Match 19)\n27 Apr","HomeName":"Nepal","AwayName":"Qatar","HomeScore":"157(40.3)","AwayScore":"89(25.1)","MatchInfo":{"Event":"ACC Men's Premier Cup ACC Premier Cup","This Match":"Match 19","Starts (venue)":"09:00, 27 April 2023","Starts (GMT)":"03:15, 27 April 2023","Toss":"Qatar won the toss and chose to field","Country":"Nepal","City":"Kirtipur","Venue":"Tribhuvan University International Cricket Ground","Umpire 1":"Naresh D'Souza","Umpire 2":"Vinod Babu","TV Umpire":"Aasif Iqbal","Referee":"Sarika Prasad"},"HomePlayers":["Rohit Paudel (C)","Aasif Sheikh (†)","Dipendra Airee","Sompal Kami","Kushal Bhurtel","Lalit Rajbanshi","Bhim Sharki","Sandeep Lamichhane","Kushal Malla","Aarif Sheikh","Gulsan Jha"],"AwayPlayers":["Zaheer Ibrahim","Kamran Khan","Imal Liyanage (†)","Mohammad Iqbar (C)","Muhammad Tanveer","Khurram Shahzad","Amir Farooq","Valeed Veetil","Mohammad Khan","Gayan Munaweera","Owais Ahmed"],"Summary":[],"Table":[["#","GROUP A","M","W","L","T","N/R","PTS","NRR","#","GROUP B","M","W","L","T","N/R","PTS","NRR"],["1","Nepal","4","3","0","0","1","7","1.497"],["2","Oman","4","3","1","0","0","6","0.377"],["3","Malaysia","4","2","2","0","0","4","0.240"],["4","Saudi Arabia","4","1","2","0","1","3","-1.101"],["5","Qatar","4","0","4","0","0","0","-1.056"],["1","United Arab Emirates","4","3","1","0","0","6","2.468"],["2","Hong Kong","3","2","0","0","1","5","2.204"],["3","Kuwait","3","2","1","0","0","4","0.072"],["4","Bahrain","4","1","2","0","1","3","0.019"],["5","Singapore","4","0","4","0","0","0","-3.028"]]}